{
  "bundleID" : "CommonSupport",
  "nonSymbolPaths" : {
    "1" : "\/tutorials\/CommonSupport",
    "5" : "\/tutorials"
  },
  "pathHierarchy" : {
    "articlesContainer" : 0,
    "modules" : [
      0
    ],
    "nodes" : [
      {
        "children" : [
          {
            "hash" : "83qp",
            "kind" : "module.extension",
            "nodeID" : 3
          }
        ],
        "name" : "CommonSupport",
        "symbolID" : {
          "interfaceLanguage" : "swift",
          "precise" : "CommonSupport"
        }
      },
      {
        "name" : "CommonSupport"
      },
      {
        "name" : "nonisolatedUnsafe(_:)",
        "symbolID" : {
          "interfaceLanguage" : "swift",
          "precise" : "s:ScM13CommonSupportE17nonisolatedUnsafeyxxyYbScMYcXEs8SendableRzlFZ"
        }
      },
      {
        "children" : [
          {
            "hash" : "52mi8",
            "kind" : "class.extension",
            "nodeID" : 4
          }
        ],
        "name" : "_Concurrency",
        "symbolID" : {
          "interfaceLanguage" : "swift",
          "precise" : "s:m:s:e:s:ScM13CommonSupportE17nonisolatedUnsafeyxxyYbScMYcXEs8SendableRzlFZ"
        }
      },
      {
        "children" : [
          {
            "hash" : "8j0fs",
            "kind" : "type.method",
            "nodeID" : 2,
            "parameterTypes" : [
              "MainActor()->T"
            ],
            "returnTypes" : [
              "T"
            ]
          }
        ],
        "name" : "MainActor",
        "symbolID" : {
          "interfaceLanguage" : "swift",
          "precise" : "s:e:s:ScM13CommonSupportE17nonisolatedUnsafeyxxyYbScMYcXEs8SendableRzlFZ"
        }
      },
      {
        "name" : "tutorials"
      }
    ],
    "tutorialContainer" : 1,
    "tutorialOverviewContainer" : 5
  },
  "version" : {
    "major" : 0,
    "minor" : 1,
    "patch" : 0
  }
}